MANIFEST.in
README.md
setup.py
geprofiler/__init__.py
geprofiler/__main__.py
geprofiler/frame.py
geprofiler/middleware.py
geprofiler/processors.py
geprofiler/profiler.py
geprofiler/py.typed
geprofiler/session.py
geprofiler/stack_sampler.py
geprofiler/typing.py
geprofiler/util.py
geprofiler.egg-info/PKG-INFO
geprofiler.egg-info/SOURCES.txt
geprofiler.egg-info/dependency_links.txt
geprofiler.egg-info/entry_points.txt
geprofiler.egg-info/not-zip-safe
geprofiler.egg-info/requires.txt
geprofiler.egg-info/top_level.txt
geprofiler/low_level/stat_profile.c
geprofiler/magic/__init__.py
geprofiler/magic/_utils.py
geprofiler/magic/magic.py
geprofiler/renderers/__init__.py
geprofiler/renderers/base.py
geprofiler/renderers/html.py
geprofiler/renderers/jsonrenderer.py
geprofiler/renderers/html_resources/app.js
geprofiler/vendor/__init__.py
geprofiler/vendor/decorator.py
html_renderer/package-lock.json
html_renderer/package.json
html_renderer/vue.config.js
html_renderer/public/index.html
html_renderer/public/sample.json
html_renderer/src/App.vue
html_renderer/src/Frame.vue
html_renderer/src/Header.vue
html_renderer/src/appState.js
html_renderer/src/main.js
html_renderer/src/assets/favicon.png
html_renderer/src/model/Frame.js
html_renderer/src/model/Group.js