Metadata-Version: 2.1
Name: geprofiler
Version: 1.0.7
Summary: Geprofiler is a Python HTTP Server profiler that makes it easy to find slow code.
Home-page: https://github.com/phamtrongngh/geprofiler
Author: Ben Pham
Author-email: benalpha1105@gmail.com
License: UNKNOWN
Keywords: profiling,profile,profiler,cpu,time,sampling
Platform: UNKNOWN
Classifier: Environment :: Console
Classifier: Environment :: Web Environment
Classifier: Intended Audience :: Developers
Classifier: License :: OSI Approved :: BSD License
Classifier: Operating System :: MacOS
Classifier: Operating System :: Microsoft :: Windows
Classifier: Operating System :: POSIX
Classifier: Topic :: Software Development :: Debuggers
Classifier: Topic :: Software Development :: Testing
Requires-Python: >=3.7
Provides-Extra: jupyter
